src/legacy/axi_lite_sub.sv
// Making this for AXI5-LITE
`timescale 1ns/1ps

module axi_lite_sub #(
    parameter ADDR_W = 32,
    parameter DATA_W = 32,
    parameter int BYTES  = DATA_W/8,

    parameter int MEM_BYTES = 256 //reduced for PnR
)(
    input logic ACLK,
    input logic ARESETn,

    // Write address channel (AW)
    input logic AWVALID,
    output logic AWREADY,
    input logic [ADDR_W-1:0] AWADDR,


    // Write data channel (W)
    input logic WVALID,
    output logic WREADY,
    input logic [DATA_W-1:0] WDATA,
    input logic [DATA_W/8-1:0] WSTRB,


    // Write response channel (B)
    input logic BREADY,
    output logic BVALID,
    output logic [1:0]  BRESP,

    // Read address channel (AR)
    input logic ARVALID,
    output logic ARREADY,
    input logic [ADDR_W-1:0] ARADDR,

    // Read data channel (R)
    output logic RVALID,
    input logic RREADY,
    output logic [DATA_W-1:0] RDATA,
    output logic [1:0]   RRESP
);

    // memory parameters 
    localparam DEPTH = MEM_BYTES / BYTES; // e.g., 4096 / 4 = 1024 words
    localparam IDX_W = (DEPTH > 1) ? $clog2(DEPTH) : 1;
    logic [DATA_W-1:0] regs [DEPTH];

    enum {W_IDLE, W_RESP} curr_write_state, next_write_state;
    enum {R_IDLE, R_RESP} curr_read_state, next_read_state;

    logic aw_pending, w_pending, ar_pending;

    // Write Address Latches
    logic [ADDR_W-1:0] saved_AWADDR;

    // Write Data Latches
    logic [DATA_W-1:0] saved_WDATA;
    logic [DATA_W/8-1:0] saved_WSTRB;

    // Read Address Latches
    logic [ADDR_W-1:0] saved_ARADDR;

    // decode word index from saved addresses (use wire so continuous assign is valid)
    wire [IDX_W-1:0] widx = saved_AWADDR[IDX_W+1:2];
    wire [IDX_W-1:0] ridx = saved_ARADDR[IDX_W+1:2];

    // output ready signals (single outstanding write/read)
    assign AWREADY = !aw_pending && !BVALID;
    assign WREADY  = !w_pending && !BVALID;
    assign ARREADY = !ar_pending && !RVALID;

    // fire signals
    logic write_fire, read_fire;
    assign write_fire = aw_pending && w_pending && !BVALID;
    assign read_fire  = ar_pending && !RVALID;

    // Default responses: OKAY
    // Keep as simple combinational drive so BRESP/RRESP are always valid values
    always_comb begin
        BRESP = 2'b00; // OKAY
        RRESP = 2'b00; // OKAY
    end


    // ARESETn may be asserted asynchronously but only deasserted synchronous
    // Two FSMs one for WRITE and one for READ
    always_ff @(posedge ACLK or negedge ARESETn) begin
        if (!ARESETn) begin
            curr_write_state <= W_IDLE;
            curr_read_state  <= R_IDLE;
        end
        else begin
            curr_write_state <= next_write_state;
            curr_read_state  <= next_read_state;
        end
    end

    // comb logic purely for state transitions
    always_comb begin
        next_write_state = curr_write_state;
        case(curr_write_state)
            W_IDLE: begin
                if (write_fire)
                    next_write_state = W_RESP;
            end

            W_RESP: begin
                if (BVALID & BREADY)
                    next_write_state = W_IDLE;
            end
        endcase

        next_read_state = curr_read_state;
        case(curr_read_state)
            R_IDLE: begin
                if (read_fire)
                    next_read_state = R_RESP;
            end

            R_RESP: begin
                if (RVALID && RREADY)
                    next_read_state = R_IDLE;
            end
        endcase
    end

    // setting internal pending signals
    always_ff @(posedge ACLK or negedge ARESETn) begin
        if (!ARESETn) begin
            aw_pending <= 0;
            w_pending  <= 0;
            ar_pending <= 0;
        end else begin
            if (AWREADY & AWVALID)
                aw_pending <= 1;

            if (WREADY & WVALID)
                w_pending <= 1;

            if (ARREADY & ARVALID)
                ar_pending <= 1;

            // clear write pendings on response acceptance
            if (BREADY & BVALID) begin
                aw_pending <= 0;
                w_pending  <= 0;
            end

            if (RREADY & RVALID)
                ar_pending <= 0;
        end
    end

    // capturing addresses, data, and ids (only on handshakes)
    always_ff @(posedge ACLK or negedge ARESETn) begin
        if (!ARESETn) begin
            saved_AWADDR <= '0;
            saved_WDATA  <= '0;
            saved_WSTRB  <= '0;
            saved_ARADDR <= '0;
        end else begin
            case (curr_write_state)
                W_IDLE: begin
                    if (AWVALID && AWREADY) begin
                        saved_AWADDR <= AWADDR;
                    end

                    if (WVALID && WREADY) begin
                        saved_WDATA <= WDATA;
                        saved_WSTRB <= WSTRB;
                    end
                end
                default: begin
                end
            endcase

            case (curr_read_state)
                R_IDLE: begin
                    if (ARVALID && ARREADY)
                        saved_ARADDR <= ARADDR;
                end
            endcase
        end
    end

    // changing internal memory and response generation
    always_ff @(posedge ACLK or negedge ARESETn) begin
        if (!ARESETn) begin
            // initialize entire memory using DEPTH
            for (int i = 0; i < DEPTH; i = i + 1)
                regs[i] = '0;

            BVALID <= 0;
            RDATA <= '0;
            RVALID <= 0;
        end else begin
            // WRITE: apply saved_WSTRB to only update selected bytes
            if (write_fire) begin
                // apply byte strobes
                // each byte chunk is 8 bits
                logic [DATA_W-1:0] new_word;
                new_word = regs[widx]; // current word
                for (int b = 0; b < BYTES; b = b + 1) begin
                    if (saved_WSTRB[b]) begin
                        new_word[8*b +: 8] = saved_WDATA[8*b +: 8];
                    end
                end
                regs[widx] <= new_word;
                BVALID <= 1;
            end

            if (BVALID && BREADY)
                BVALID <= 0;

            // READ
            if (read_fire) begin
                RDATA <= regs[ridx];
                RVALID <= 1;
            end

            if (RVALID && RREADY)
                RVALID <= 0;
        end
    end

endmodule

tb/axi_lite_sub_tb.sv
`timescale 1ns/1ps

module axi_lite_sub_tb;
    localparam int ADDR_W = 32;
    localparam int DATA_W = 32;
    localparam int DEPTH  = 128;
    localparam time CLK_PERIOD = 10ns;

    logic ACLK;
    logic ARESETn;

    logic AWVALID;
    logic AWREADY;
    logic [ADDR_W-1:0] AWADDR;

    logic WVALID;
    logic WREADY;
    logic [DATA_W-1:0] WDATA;
    logic [DATA_W/8-1:0] WSTRB;

    logic BVALID;
    logic BREADY;

    logic ARVALID;
    logic ARREADY;
    logic [ADDR_W-1:0] ARADDR;

    logic RVALID;
    logic RREADY;
    logic [DATA_W-1:0] RDATA;

    logic [DATA_W-1:0] exp_mem [0:DEPTH-1];
    int checks_total;
    int checks_failed;

    axi_lite_sub #(
        .ADDR_W(ADDR_W),
        .DATA_W(DATA_W)
    ) dut (
        .ACLK(ACLK),
        .ARESETn(ARESETn),
        .AWVALID(AWVALID),
        .AWREADY(AWREADY),
        .AWADDR(AWADDR),
        .WVALID(WVALID),
        .WREADY(WREADY),
        .WDATA(WDATA),
        .WSTRB(WSTRB),
        .BVALID(BVALID),
        .BREADY(BREADY),
        .ARVALID(ARVALID),
        .ARREADY(ARREADY),
        .ARADDR(ARADDR),
        .RVALID(RVALID),
        .RREADY(RREADY),
        .RDATA(RDATA)
    );

    always #(CLK_PERIOD/2) ACLK = ~ACLK;

    task automatic check(input bit cond, input string msg);
        begin
            checks_total++;
            if (!cond) begin
                checks_failed++;
                $error("CHECK FAILED: %s (t=%0t)", msg, $time);
            end
        end
    endtask

    task automatic init_drives;
        begin
            AWVALID = 1'b0;
            AWADDR  = '0;
            WVALID  = 1'b0;
            WDATA   = '0;
            WSTRB   = '0;
            BREADY  = 1'b0;
            ARVALID = 1'b0;
            ARADDR  = '0;
            RREADY  = 1'b0;
        end
    endtask

    task automatic init_exp_mem;
        int i;
        begin
            for (i = 0; i < DEPTH; i++) begin
                exp_mem[i] = '0;
            end
        end
    endtask

    task automatic do_reset;
        begin
            ARESETn = 1'b0;
            init_drives();
            init_exp_mem();
            repeat (4) @(posedge ACLK);
            ARESETn = 1'b1;
            @(posedge ACLK);
        end
    endtask

    task automatic write_addr_phase(
        input logic [ADDR_W-1:0] addr,
        input int delay_cycles
    );
        int timeout;
        begin
            repeat (delay_cycles) @(posedge ACLK);
            AWADDR  <= addr;
            AWVALID <= 1'b1;
            timeout = 0;
            while (!(AWVALID && AWREADY)) begin
                @(posedge ACLK);
                timeout++;
                if (timeout > 100) $fatal(1, "AW handshake timeout");
            end
            AWVALID <= 1'b0;
        end
    endtask

    task automatic write_data_phase(
        input logic [DATA_W-1:0] data,
        input logic [DATA_W/8-1:0] strb,
        input int delay_cycles
    );
        int timeout;
        begin
            repeat (delay_cycles) @(posedge ACLK);
            WDATA  <= data;
            WSTRB  <= strb;
            WVALID <= 1'b1;
            timeout = 0;
            while (!(WVALID && WREADY)) begin
                @(posedge ACLK);
                timeout++;
                if (timeout > 100) $fatal(1, "W handshake timeout");
            end
            WVALID <= 1'b0;
        end
    endtask

    task automatic write_response_phase(input int bready_delay);
        int timeout;
        begin
            BREADY <= 1'b0;
            repeat (bready_delay) @(posedge ACLK);
            BREADY <= 1'b1;
            timeout = 0;
            while (!BVALID) begin
                @(posedge ACLK);
                timeout++;
                if (timeout > 100) $fatal(1, "BVALID timeout");
            end
            @(posedge ACLK);
            BREADY <= 1'b0;
        end
    endtask

    task automatic issue_write_no_resp(
        input logic [ADDR_W-1:0] addr,
        input logic [DATA_W-1:0] data,
        input logic [DATA_W/8-1:0] strb,
        input int aw_delay,
        input int w_delay
    );
        begin
            fork
                write_addr_phase(addr, aw_delay);
                write_data_phase(data, strb, w_delay);
            join
        end
    endtask

    task automatic axi_write(
        input logic [ADDR_W-1:0] addr,
        input logic [DATA_W-1:0] data,
        input logic [DATA_W/8-1:0] strb,
        input int aw_delay,
        input int w_delay,
        input int bready_delay
    );
        begin
            issue_write_no_resp(addr, data, strb, aw_delay, w_delay);
            write_response_phase(bready_delay);
            exp_mem[addr] = data;
        end
    endtask

    task automatic axi_read(
        input logic [ADDR_W-1:0] addr,
        input int ar_delay,
        input int rready_delay,
        output logic [DATA_W-1:0] data
    );
        int timeout;
        begin
            repeat (ar_delay) @(posedge ACLK);
            ARADDR  <= addr;
            ARVALID <= 1'b1;
            timeout = 0;
            while (!(ARVALID && ARREADY)) begin
                @(posedge ACLK);
                timeout++;
                if (timeout > 100) $fatal(1, "AR handshake timeout");
            end
            ARVALID <= 1'b0;

            RREADY <= 1'b0;
            repeat (rready_delay) @(posedge ACLK);
            RREADY <= 1'b1;
            timeout = 0;
            while (!RVALID) begin
                @(posedge ACLK);
                timeout++;
                if (timeout > 100) $fatal(1, "RVALID timeout");
            end
            data = RDATA;
            @(posedge ACLK);
            RREADY <= 1'b0;
        end
    endtask

    task automatic test_write_and_read(
        input logic [ADDR_W-1:0] addr,
        input logic [DATA_W-1:0] data,
        input int aw_delay,
        input int w_delay
    );
        logic [DATA_W-1:0] rd;
        begin
            axi_write(addr, data, '1, aw_delay, w_delay, 0);
            axi_read(addr, 0, 0, rd);
            check(rd === exp_mem[addr], $sformatf("Readback mismatch at addr=%0d", addr));
        end
    endtask

    task automatic test_b_backpressure;
        int timeout;
        begin
            issue_write_no_resp(32'd21, 32'hBEEF_0021, '1, 0, 0);
            exp_mem[21] = 32'hBEEF_0021;

            timeout = 0;
            while (!BVALID) begin
                @(posedge ACLK);
                timeout++;
                if (timeout > 100) $fatal(1, "BVALID timeout in backpressure test");
            end

            repeat (3) begin
                @(posedge ACLK);
                check(BVALID === 1'b1, "BVALID must stay high while BREADY is low");
            end

            BREADY <= 1'b1;
            @(posedge ACLK);
            BREADY <= 1'b0;
            @(posedge ACLK);
            check(BVALID === 1'b0, "BVALID should clear after response handshake");
        end
    endtask

    task automatic test_r_backpressure;
        logic [DATA_W-1:0] rd;
        int timeout;
        begin
            axi_write(32'd25, 32'hCAFE_0025, '1, 0, 0, 0);

            ARADDR  <= 32'd25;
            ARVALID <= 1'b1;
            timeout = 0;
            while (!(ARVALID && ARREADY)) begin
                @(posedge ACLK);
                timeout++;
                if (timeout > 100) $fatal(1, "AR timeout in backpressure test");
            end
            ARVALID <= 1'b0;
            RREADY  <= 1'b0;

            timeout = 0;
            while (!RVALID) begin
                @(posedge ACLK);
                timeout++;
                if (timeout > 100) $fatal(1, "RVALID timeout in backpressure test");
            end

            repeat (3) begin
                @(posedge ACLK);
                check(RVALID === 1'b1, "RVALID must stay high while RREADY is low");
            end

            RREADY <= 1'b1;
            rd = RDATA;
            @(posedge ACLK);
            RREADY <= 1'b0;
            @(posedge ACLK);

            check(rd === exp_mem[25], "RDATA mismatch in read backpressure test");
            check(RVALID === 1'b0, "RVALID should clear after read handshake");
        end
    endtask

    initial begin
        logic [DATA_W-1:0] rd_data;

        $dumpfile("tb/axi_lite_sub_tb.vcd");
        $dumpvars(0, axi_lite_sub_tb);

        ACLK = 1'b0;
        checks_total = 0;
        checks_failed = 0;

        do_reset();
        check(BVALID === 1'b0, "BVALID should be low after reset");
        check(RVALID === 1'b0, "RVALID should be low after reset");
        check(AWREADY === 1'b1, "AWREADY should be high after reset");
        check(WREADY === 1'b1, "WREADY should be high after reset");
        check(ARREADY === 1'b1, "ARREADY should be high after reset");

        test_write_and_read(32'd3, 32'hA5A5_0003, 0, 0);
        test_write_and_read(32'd7, 32'hA5A5_0007, 0, 3);
        test_write_and_read(32'd9, 32'hA5A5_0009, 3, 0);

        axi_read(32'd3, 2, 2, rd_data);
        check(rd_data === exp_mem[3], "Delayed read mismatch");

        test_b_backpressure();
        test_r_backpressure();

        if (checks_failed == 0) begin
            $display("PASS: %0d checks passed", checks_total);
        end else begin
            $fatal(1, "FAIL: %0d/%0d checks failed", checks_failed, checks_total);
        end

        repeat (2) @(posedge ACLK);
        $finish;
    end

endmodule

tb/axi_lite_sub_tb.vcd
$date
	Thu Apr 16 19:43:39 2026
$end
$version
	Icarus Verilog
$end
$timescale
	1ps
$end
$scope module axi_lite_sub_tb $end
$var wire 1 ! WREADY $end
$var wire 1 " RVALID $end
$var wire 32 # RDATA [31:0] $end
$var wire 1 $ BVALID $end
$var wire 1 % AWREADY $end
$var wire 1 & ARREADY $end
$var parameter 32 ' ADDR_W $end
$var parameter 64 ( CLK_PERIOD $end
$var parameter 32 ) DATA_W $end
$var parameter 32 * DEPTH $end
$var reg 1 + ACLK $end
$var reg 32 , ARADDR [31:0] $end
$var reg 1 - ARESETn $end
$var reg 1 . ARVALID $end
$var reg 32 / AWADDR [31:0] $end
$var reg 1 0 AWVALID $end
$var reg 1 1 BREADY $end
$var reg 1 2 RREADY $end
$var reg 32 3 WDATA [31:0] $end
$var reg 4 4 WSTRB [3:0] $end
$var reg 1 5 WVALID $end
$var integer 32 6 checks_failed [31:0] $end
$var integer 32 7 checks_total [31:0] $end
$scope module dut $end
$var wire 1 + ACLK $end
$var wire 32 8 ARADDR [31:0] $end
$var wire 1 - ARESETn $end
$var wire 1 & ARREADY $end
$var wire 1 . ARVALID $end
$var wire 32 9 AWADDR [31:0] $end
$var wire 1 % AWREADY $end
$var wire 1 0 AWVALID $end
$var wire 1 1 BREADY $end
$var wire 1 2 RREADY $end
$var wire 32 : WDATA [31:0] $end
$var wire 1 ! WREADY $end
$var wire 4 ; WSTRB [3:0] $end
$var wire 1 5 WVALID $end
$var wire 1 < read_fire $end
$var wire 1 = write_fire $end
$var wire 6 > widx [5:0] $end
$var wire 6 ? ridx [5:0] $end
$var parameter 32 @ ADDR_W $end
$var parameter 32 A BYTES $end
$var parameter 32 B DATA_W $end
$var parameter 32 C DEPTH $end
$var parameter 32 D IDX_W $end
$var parameter 32 E MEM_BYTES $end
$var reg 2 F BRESP [1:0] $end
$var reg 1 $ BVALID $end
$var reg 32 G RDATA [31:0] $end
$var reg 2 H RRESP [1:0] $end
$var reg 1 " RVALID $end
$var reg 1 I ar_pending $end
$var reg 1 J aw_pending $end
$var reg 32 K saved_ARADDR [31:0] $end
$var reg 32 L saved_AWADDR [31:0] $end
$var reg 32 M saved_WDATA [31:0] $end
$var reg 4 N saved_WSTRB [3:0] $end
$var reg 1 O w_pending $end
$var integer 32 P curr_read_state [31:0] $end
$var integer 32 Q curr_write_state [31:0] $end
$var integer 32 R next_read_state [31:0] $end
$var integer 32 S next_write_state [31:0] $end
$scope begin $ivl_for_loop0 $end
$var integer 32 T i [31:0] $end
$upscope $end
$scope begin $unm_blk_25 $end
$var reg 32 U new_word [31:0] $end
$scope begin $ivl_for_loop1 $end
$var integer 32 V b [31:0] $end
$upscope $end
$upscope $end
$upscope $end
$scope begin $unm_blk_55 $end
$var reg 32 W rd_data [31:0] $end
$upscope $end
$scope task axi_read $end
$upscope $end
$scope task axi_write $end
$upscope $end
$scope task check $end
$upscope $end
$scope task do_reset $end
$upscope $end
$scope task init_drives $end
$upscope $end
$scope task init_exp_mem $end
$upscope $end
$scope task issue_write_no_resp $end
$upscope $end
$scope task test_b_backpressure $end
$upscope $end
$scope task test_r_backpressure $end
$upscope $end
$scope task test_write_and_read $end
$upscope $end
$scope task write_addr_phase $end
$upscope $end
$scope task write_data_phase $end
$upscope $end
$scope task write_response_phase $end
$upscope $end
$upscope $end
$enddefinitions $end
$comment Show the parameter values. $end
$dumpall
b100000000 E
b110 D
b1000000 C
b100000 B
b100 A
b100000 @
b10000000 *
b100000 )
b1010 (
b100000 '
$end
#0
$dumpvars
bx W
b0 V
bx U
b1000000 T
b0 S
b0 R
b0 Q
b0 P
0O
b0 N
b0 M
b0 L
b0 K
0J
0I
b0 H
b0 G
b0 F
b0 ?
b0 >
0=
0<
b0 ;
b0 :
b0 9
b0 8
b0 7
b0 6
05
b0 4
b0 3
02
01
00
b0 /
0.
0-
b0 ,
0+
1&
1%
0$
b0 #
0"
1!
$end
#5000
b1000000 T
1+
#10000
0+
#15000
b1000000 T
1+
#20000
0+
#25000
b1000000 T
1+
#30000
0+
#35000
1-
1+
#40000
0+
#45000
10
b11 /
b11 9
15
b1111 4
b1111 ;
b10100101101001010000000000000011 3
b10100101101001010000000000000011 :
b101 7
1+
#50000
0+
#55000
b1 S
1=
0!
0%
1O
1J
b1111 N
b10100101101001010000000000000011 M
b11 L
11
05
00
1+
#60000
0+
#65000
0=
b0 S
1$
b1 Q
b100 V
b10100101101001010000000000000011 U
1+
#70000
0+
#75000
b0 S
1%
1!
0=
b0 Q
0O
0J
0$
1+
#80000
0+
#85000
1.
b11 ,
b11 8
01
1+
#90000
0+
#95000
b1 R
0&
1<
1I
b11 K
12
0.
1+
#100000
0+
#105000
0<
b0 R
1"
b10100101101001010000000000000011 #
b10100101101001010000000000000011 G
b1 P
1+
#110000
0+
#115000
1&
b0 P
0I
0"
1+
#120000
0+
#125000
10
b111 /
b111 9
02
b110 7
1+
#130000
0+
#135000
0%
b1 >
1J
b111 L
00
1+
#140000
0+
#145000
1+
#150000
0+
#155000
15
b10100101101001010000000000000111 3
b10100101101001010000000000000111 :
1+
#160000
0+
#165000
b1 S
1=
0!
b10100101101001010000000000000111 M
1O
11
05
1+
#170000
0+
#175000
0=
b0 S
1$
b1 Q
b100 V
b10100101101001010000000000000111 U
1+
#180000
0+
#185000
b0 S
1%
1!
0=
0O
0J
b0 Q
0$
1+
#190000
0+
#195000
1.
b111 ,
b111 8
01
1+
#200000
0+
#205000
b1 R
b1 ?
0&
1<
b111 K
1I
12
0.
1+
#210000
0+
#215000
0<
b0 R
1"
b10100101101001010000000000000111 #
b10100101101001010000000000000111 G
b1 P
1+
#220000
0+
#225000
1&
0I
b0 P
0"
1+
#230000
0+
#235000
15
b10100101101001010000000000001001 3
b10100101101001010000000000001001 :
02
b111 7
1+
#240000
0+
#245000
0!
b10100101101001010000000000001001 M
1O
05
1+
#250000
0+
#255000
1+
#260000
0+
#265000
10
b1001 /
b1001 9
1+
#270000
0+
#275000
b1 S
1=
0%
b10 >
1J
b1001 L
11
00
1+
#280000
0+
#285000
0=
b0 S
1$
b1 Q
b100 V
b10100101101001010000000000001001 U
1+
#290000
0+
#295000
b0 S
1%
1!
0=
b0 Q
0O
0J
0$
1+
#300000
0+
#305000
1.
b1001 ,
b1001 8
01
1+
#310000
0+
#315000
b1 R
0&
1<
b10 ?
1I
b1001 K
12
0.
1+
#320000
0+
#325000
0<
b0 R
1"
b10100101101001010000000000001001 #
b10100101101001010000000000001001 G
b1 P
1+
#330000
0+
#335000
1&
b0 P
0I
0"
1+
#340000
0+
#345000
02
b1000 7
1+
#350000
0+
#355000
1+
#360000
0+
#365000
1.
b11 ,
b11 8
1+
#370000
0+
#375000
b1 R
0&
1<
b0 ?
1I
b11 K
0.
1+
#380000
0+
#385000
0<
1"
b10100101101001010000000000000011 #
b10100101101001010000000000000011 G
b1 P
1+
#390000
0+
#395000
b0 R
12
1+
#400000
0+
#405000
1&
0"
0I
b0 P
10
b10101 /
b10101 9
15
b10111110111011110000000000100001 3
b10111110111011110000000000100001 :
02
b1001 7
b10100101101001010000000000000011 W
1+
#410000
0+
#415000
b1 S
1=
0!
0%
b101 >
1O
1J
b10111110111011110000000000100001 M
b10101 L
05
00
1+
#420000
0+
#425000
0=
1$
b1 Q
b100 V
b10111110111011110000000000100001 U
1+
#430000
0+
#435000
1+
#440000
0+
#445000
b1010 7
1+
#450000
0+
#455000
b1011 7
1+
#460000
0+
#465000
b0 S
11
b1100 7
1+
#470000
0+
#475000
b0 S
1%
1!
0=
b0 Q
0O
0J
0$
01
1+
#480000
0+
#485000
10
b11001 /
b11001 9
15
b11001010111111100000000000100101 3
b11001010111111100000000000100101 :
b1101 7
1+
#490000
0+
#495000
b1 S
1=
0!
0%
b110 >
1O
1J
b11001010111111100000000000100101 M
b11001 L
11
05
00
1+
#500000
0+
#505000
0=
b0 S
1$
b1 Q
b100 V
b11001010111111100000000000100101 U
1+
#510000
0+
#515000
b0 S
1%
1!
0=
b0 Q
0O
0J
0$
1+
#520000
0+
#525000
1.
b11001 ,
b11001 8
01
1+
#530000
0+
#535000
b1 R
0&
1<
b110 ?
1I
b11001 K
0.
1+
#540000
0+
#545000
0<
1"
b11001010111111100000000000100101 #
b11001010111111100000000000100101 G
b1 P
1+
#550000
0+
#555000
1+
#560000
0+
#565000
b1110 7
1+
#570000
0+
#575000
b1111 7
1+
#580000
0+
#585000
b0 R
12
b10000 7
1+
#590000
0+
#595000
1&
b0 P
0I
0"
02
1+
#600000
0+
#605000
b10010 7
1+
